aidge_backend_cuda/aidge_backend_cuda.cpython-311-x86_64-linux-gnu.so
aidge_backend_cuda/__init__.py
aidge_backend_cuda/version.txt
aidge_backend_cuda/benchmark/__init__.py
aidge_backend_cuda/benchmark/registrations/__init__.py
aidge_backend_cuda/benchmark/registrations/extensions_inference/aidge_backend_cuda.py
aidge_backend_cuda/benchmark/registrations/extensions_inference/__init__.py
aidge_backend_cuda-0.8.0.dist-info/RECORD
aidge_backend_cuda-0.8.0.dist-info/top_level.txt
aidge_backend_cuda-0.8.0.dist-info/METADATA
aidge_backend_cuda-0.8.0.dist-info/WHEEL
aidge_backend_cuda-0.8.0.dist-info/licenses/LICENSE
aidge_backend_cuda.libs/libcurand-f9bea038.so.10.3.9.90
aidge_backend_cuda.libs/libgomp-24e2ab19.so.1.0.0
