Metadata-Version: 2.4
Name: aidge_backend_cuda
Version: 0.8.0
Summary: CUDA implementations of the operators of aidge framework
License: Eclipse Public License - v 2.0
Project-URL: Homepage, https://www.deepgreen.ai/en/platform
Project-URL: Documentation, https://eclipse.dev/aidge/
Project-URL: Repository, https://gitlab.eclipse.org/eclipse/aidge/aidge_backend_cuda
Project-URL: Issues, https://gitlab.eclipse.org/eclipse/aidge/aidge_backend_cuda/-/issues
Project-URL: Changelog, https://gitlab.eclipse.org/eclipse/aidge/aidge_backend_cuda/-/releases
Classifier: Development Status :: 2 - Pre-Alpha
Classifier: Programming Language :: Python :: 3
Requires-Python: >=3.10
License-File: LICENSE
Requires-Dist: numpy
Dynamic: license-file
